greeum/__init__.py
greeum/__main__.py
greeum/cli.py
greeum/client.py
greeum/config_store.py
greeum/embedding_models.py
greeum/knowledge_graph.py
greeum/memory_evolution.py
greeum/py.typed
greeum/temporal_reasoner.py
greeum/text_utils.py
greeum/token_utils.py
greeum/utils.py
greeum/anchors/__init__.py
greeum/anchors/auto_movement.py
greeum/anchors/manager.py
greeum/anchors/schema.py
greeum/api/__init__.py
greeum/api/anchors.py
greeum/api/write.py
greeum/automation/__init__.py
greeum/automation/digest.py
greeum/automation/workflow.py
greeum/automation/workflow_guide.md
greeum/cli/__init__.py
greeum/cli/__main__.py
greeum/cli/anchors.py
greeum/cli/backup_restore_cli.py
greeum/cli/dashboard_cli.py
greeum/cli/doctor.py
greeum/cli/graph.py
greeum/cli/merge_cli.py
greeum/cli/metrics_cli.py
greeum/cli/validate_cli.py
greeum/client/__init__.py
greeum/client/client.py
greeum/client/http_client.py
greeum/client/stm_cache.py
greeum/core/__init__.py
greeum/core/association_network.py
greeum/core/backup_restore.py
greeum/core/block_manager.py
greeum/core/bm25_index.py
greeum/core/branch_auto_merge.py
greeum/core/branch_aware_storage.py
greeum/core/branch_global_index.py
greeum/core/branch_index.py
greeum/core/branch_manager.py
greeum/core/branch_schema.py
greeum/core/cache_manager.py
greeum/core/checkpoint_manager.py
greeum/core/config.py
greeum/core/context_classifier.py
greeum/core/context_manager.py
greeum/core/context_memory.py
greeum/core/dashboard.py
greeum/core/database_manager.py
greeum/core/db_integrity.py
greeum/core/dfs_search.py
greeum/core/doc_validator.py
greeum/core/duplicate_detector.py
greeum/core/global_index.py
greeum/core/graph_bootstrap.py
greeum/core/hybrid_graph_search.py
greeum/core/insight_filter.py
greeum/core/insight_judge.py
greeum/core/insight_pipeline.py
greeum/core/ltm_layer.py
greeum/core/ltm_links_cache.py
greeum/core/memory_indexer.py
greeum/core/memory_layer.py
greeum/core/merge_engine.py
greeum/core/metrics.py
greeum/core/project_manager.py
greeum-5.1.0.dist-info/METADATA
greeum-5.1.0.dist-info/WHEEL
greeum-5.1.0.dist-info/entry_points.txt
greeum-5.1.0.dist-info/top_level.txt
greeum-5.1.0.dist-info/RECORD
