Metadata-Version: 2.4
Name: greeum
Version: 5.1.0
Summary: LLM-Integrated Memory System with InsightJudge, HybridGraphSearch, and Branch-aware Storage
Author-email: DryRainEnt <kachirjsdn@gmail.com>
Keywords: memory,LLM,RAG
Classifier: Programming Language :: Python :: 3
Classifier: Programming Language :: Python :: 3.10
Classifier: Programming Language :: Python :: 3.11
Classifier: Programming Language :: Python :: 3.12
Classifier: Programming Language :: Python :: 3.13
Classifier: Development Status :: 5 - Production/Stable
Classifier: Intended Audience :: Developers
Classifier: Topic :: Software Development :: Libraries :: Python Modules
Classifier: Topic :: Scientific/Engineering :: Artificial Intelligence
Classifier: Operating System :: OS Independent
Classifier: License :: OSI Approved :: MIT License
Requires-Python: >=3.10
Requires-Dist: rich>=13.4.0
Requires-Dist: click>=8.1.0
Requires-Dist: numpy>=1.24.0
Requires-Dist: sqlalchemy>=2.0.0
Requires-Dist: pydantic>=2.0.0
Requires-Dist: anyio>=4.5
Requires-Dist: requests>=2.25.0
Requires-Dist: flask>=2.0.0
Requires-Dist: flask-restx>=0.5.1
Requires-Dist: flask-cors>=3.0.10
Requires-Dist: python-dotenv>=0.19.0
Requires-Dist: python-dateutil>=2.8.2
Requires-Dist: sentence-transformers>=2.2.0
Requires-Dist: psutil>=5.9.0
Requires-Dist: fastapi>=0.110.0
Requires-Dist: uvicorn[standard]>=0.22.0
Provides-Extra: test
Requires-Dist: pytest>=7.0; extra == "test"
Requires-Dist: pytest-cov; extra == "test"
Requires-Dist: responses>=0.23.0; extra == "test"
Provides-Extra: dev
Requires-Dist: black; extra == "dev"
Requires-Dist: isort; extra == "dev"
Requires-Dist: flake8; extra == "dev"
Requires-Dist: ruff; extra == "dev"
Provides-Extra: mcp-http
Requires-Dist: fastapi>=0.110.0; extra == "mcp-http"
Requires-Dist: uvicorn[standard]>=0.22.0; extra == "mcp-http"
Provides-Extra: full
Requires-Dist: sentence-transformers>=2.2.0; extra == "full"
Requires-Dist: openai>=0.27.0; extra == "full"
Requires-Dist: faiss-cpu>=1.7.4; extra == "full"
Requires-Dist: keybert>=0.7.0; extra == "full"
Requires-Dist: scikit-learn>=1.3.0; extra == "full"
Requires-Dist: transformers>=4.40.0; extra == "full"
Requires-Dist: spacy>=3.5.0; extra == "full"
